color_console/__init__.py
color_console/color_console.py
color_console_py-0.1.1.dist-info/LICENCE
color_console_py-0.1.1.dist-info/METADATA
color_console_py-0.1.1.dist-info/WHEEL
color_console_py-0.1.1.dist-info/top_level.txt
color_console_py-0.1.1.dist-info/RECORD
